yt_study/__init__.py
yt_study/cli.py
yt_study/config.py
yt_study/setup_wizard.py
yt_study/llm/__init__.py
yt_study/llm/generator.py
yt_study/llm/providers.py
yt_study/pipeline/__init__.py
yt_study/pipeline/orchestrator.py
yt_study/prompts/__init__.py
yt_study/prompts/chapter_notes.py
yt_study/prompts/study_notes.py
yt_study/ui/__init__.py
yt_study/ui/dashboard.py
yt_study/youtube/__init__.py
yt_study/youtube/metadata.py
yt_study/youtube/parser.py
yt_study/youtube/playlist.py
yt_study/youtube/transcript.py
yt_study-0.1.7.dist-info/METADATA
yt_study-0.1.7.dist-info/WHEEL
yt_study-0.1.7.dist-info/entry_points.txt
yt_study-0.1.7.dist-info/licenses/LICENSE
yt_study-0.1.7.dist-info/RECORD
