Metadata-Version: 2.4
Name: yt-study
Version: 0.1.7
Summary: Convert YouTube videos into AI-powered study notes with chapter support
Author-email: whoisjayd <contactjaydeepsolanki@gmail.com>
License: MIT
License-File: LICENSE
Keywords: ai,education,llm,notes,study,transcript,youtube
Classifier: Development Status :: 4 - Beta
Classifier: Intended Audience :: Education
Classifier: Intended Audience :: End Users/Desktop
Classifier: License :: OSI Approved :: MIT License
Classifier: Programming Language :: Python :: 3
Classifier: Programming Language :: Python :: 3.10
Classifier: Programming Language :: Python :: 3.11
Classifier: Programming Language :: Python :: 3.12
Classifier: Programming Language :: Python :: 3.13
Classifier: Topic :: Education
Classifier: Topic :: Multimedia :: Video
Requires-Python: >=3.10
Requires-Dist: aiohttp>=3.11.11
Requires-Dist: litellm>=1.81.1
Requires-Dist: pytubefix>=10.3.6
Requires-Dist: rich>=13.9.4
Requires-Dist: typer>=0.21.1
Requires-Dist: youtube-transcript-api>=1.2.3
